[
  {
    "bookId": 13,
    "chapterId": 2,
    "verseId": 1,
    "words": [
      {
        "word": "אֵלֶּה",
        "wordId": 1,
        "original": "אֵ֖לֶּה",
        "explanation": "Betyr 'disse' og brukes ofte for å introdusere en liste eller oppsummering, som her innleder stammefedrenes navneliste."
      },
      {
        "word": "בְּנֵי",
        "wordId": 2,
        "original": "בְּנֵ֣י",
        "explanation": "Flertallsformen av 'sønn' i konstruktform, som betyr 'sønnene til'. Brukes ofte om etterkommere generelt."
      },
      {
        "word": "יִשְׂרָאֵל",
        "wordId": 3,
        "original": "יִשְׂרָאֵ֑ל",
        "explanation": "Navnet Jakob fikk etter å ha kjempet med engelen, og betyr 'den som kjemper med Gud'. Refererer her til patriarken Jakob."
      },
      {
        "word": "רְאוּבֵן",
        "wordId": 4,
        "original": "רְאוּבֵ֤ן",
        "explanation": "Jakobs førstefødte sønn med Lea. Navnet betyr 'se, en sønn!' og reflekterer Leas glede over å føde."
      },
      {
        "word": "שִׁמְעוֹן",
        "wordId": 5,
        "original": "שִׁמְעוֹן֙",
        "explanation": "Jakobs andre sønn med Lea. Navnet kommer fra verbet 'å høre' og betyr 'han som hører' eller 'den hørte'."
      },
      {
        "word": "לֵוִי",
        "wordId": 6,
        "original": "לֵוִ֣י",
        "explanation": "Stamfar til presteslekten. Navnet betyr 'tilknyttet' eller 'forbundet', da Lea håpet dette barnet ville knytte Jakob nærmere til henne."
      },
      {
        "word": "וִיהוּדָה",
        "wordId": 7,
        "original": "וִיהוּדָ֔ה",
        "explanation": "Betyr 'pris' eller 'takksigelse' fra verbet 'å prise'. Kongeslekten og Messias skulle komme fra denne stammen."
      },
      {
        "word": "יִשָׂשכָר",
        "wordId": 8,
        "original": "יִשָׂשכָ֖ר",
        "explanation": "Jakobs niende sønn. Navnet tolkes som 'det er en belønning' og ble gitt fordi Lea så ham som lønn fra Gud."
      },
      {
        "word": "וּזְבֻלוּן",
        "wordId": 9,
        "original": "וּזְבֻלֽוּן",
        "explanation": "Leas sjette sønn med Jakob. Navnet betyr 'bolig' eller 'ære', da Lea trodde Jakob nå ville bo hos henne."
      }
    ]
  }
]