[
  {
    "bookId": 66,
    "chapterId": 14,
    "verseId": 13,
    "words": [
      {
        "word": "Καὶ",
        "wordId": 1,
        "original": "Καὶ",
        "explanation": "Konjunksjon som binder sammen hendelser i Johannes' visjon, og markerer overgangen til en ny åpenbaring."
      },
      {
        "word": "ἤκουσα",
        "wordId": 2,
        "original": "ἤκουσα",
        "explanation": "Aorist av 'akouō' - å høre. Johannes mottar her en direkte guddommelig meddelelse gjennom hørselen."
      },
      {
        "word": "φωνῆς",
        "wordId": 3,
        "original": "φωνῆς",
        "explanation": "Betyr 'røst' eller 'stemme'. I Åpenbaringen representerer himmelsk røst ofte guddommelig autoritet."
      },
      {
        "word": "ἐκ",
        "wordId": 4,
        "original": "ἐκ",
        "explanation": "Preposisjon som angir opprinnelse - røsten kommer ut fra himmelen."
      },
      {
        "word": "τοῦ",
        "wordId": 5,
        "original": "τοῦ",
        "explanation": "Bestemt artikkel i genitiv som spesifiserer 'himmelen' som kilden."
      },
      {
        "word": "οὐρανοῦ",
        "wordId": 6,
        "original": "οὐρανοῦ",
        "explanation": "Refererer til himmelen som Guds bolig, stedet for guddommelig autoritet og åpenbaring."
      },
      {
        "word": "λεγούσης",
        "wordId": 7,
        "original": "λεγούσης",
        "explanation": "Presens partisipp av 'legō' - røsten er aktivt talende, og formidler et budskap."
      },
      {
        "word": "Γράψον",
        "wordId": 8,
        "original": "Γράψον",
        "explanation": "Imperativ aorist - en direkte befaling til Johannes om å skrive ned denne viktige sannheten for ettertiden."
      },
      {
        "word": "Μακάριοι",
        "wordId": 9,
        "original": "Μακάριοι",
        "explanation": "Betyr 'salige' eller 'velsignede'. Dette er en av de syv saligprisningene i Åpenbaringen."
      },
      {
        "word": "οἱ",
        "wordId": 10,
        "original": "οἱ",
        "explanation": "Bestemt artikkel som substantiverer de følgende ordene - 'de som'."
      },
      {
        "word": "νεκροὶ",
        "wordId": 11,
        "original": "νεκροὶ",
        "explanation": "Betyr 'døde'. Her refererer det til troende som dør i troen på Kristus."
      },
      {
        "word": "οἱ",
        "wordId": 12,
        "original": "οἱ",
        "explanation": "Artikkel som innleder en nærmere beskrivelse av hvilke døde som omtales."
      },
      {
        "word": "ἐν",
        "wordId": 13,
        "original": "ἐν",
        "explanation": "Preposisjon som uttrykker sfære eller tilstand - å være 'i' Herren, i fellesskap med ham."
      },
      {
        "word": "κυρίῳ",
        "wordId": 14,
        "original": "κυρίῳ",
        "explanation": "Refererer til 'Herren', altså Jesus Kristus. Å dø 'i Herren' betyr å dø i trosfellesskap med ham."
      },
      {
        "word": "ἀποθνῄσκοντες",
        "wordId": 15,
        "original": "ἀποθνῄσκοντες",
        "explanation": "Presens partisipp av 'apothnēskō' - å dø. Formen antyder en pågående handling gjennom historien."
      },
      {
        "word": "ἀπʼ",
        "wordId": 16,
        "original": "ἀπʼ",
        "explanation": "Forkortet form av 'apo' - fra. Markerer startpunktet for velsignelsen."
      },
      {
        "word": "ἄρτι",
        "wordId": 17,
        "original": "ἄρτι",
        "explanation": "Betyr 'fra nå av' eller 'heretter'. Markerer et vendepunkt i frelseshistorien."
      },
      {
        "word": "ναί",
        "wordId": 18,
        "original": "ναί",
        "explanation": "En sterk bekreftelse - 'ja' eller 'sannelig'. Ånden bekrefter den himmelske røstens budskap."
      },
      {
        "word": "λέγει",
        "wordId": 19,
        "original": "λέγει",
        "explanation": "Presens av 'legō' - Ånden 'sier', noe som understreker den levende og aktive naturen av dette vitnesbyrdet."
      },
      {
        "word": "τὸ",
        "wordId": 20,
        "original": "τὸ",
        "explanation": "Bestemt artikkel i nøytrum som refererer til Den Hellige Ånd."
      },
      {
        "word": "πνεῦμα",
        "wordId": 21,
        "original": "πνεῦμα",
        "explanation": "Refererer til Den Hellige Ånd. Åndens bekreftelse gir budskapet guddommelig autoritet."
      },
      {
        "word": "ἵνα",
        "wordId": 22,
        "original": "ἵνα",
        "explanation": "Konjunksjon som innleder hensikten eller resultatet - 'for at' eller 'slik at'."
      },
      {
        "word": "ἀναπαήσονται",
        "wordId": 23,
        "original": "ἀναπαήσονται",
        "explanation": "Futurum av 'anapauō' - å hvile. Beskriver den evige hvilen fra jordisk strev og lidelse."
      },
      {
        "word": "ἐκ",
        "wordId": 24,
        "original": "ἐκ",
        "explanation": "Preposisjon som her betyr 'fra' - hvile bort fra eller frihet fra."
      },
      {
        "word": "τῶν",
        "wordId": 25,
        "original": "τῶν",
        "explanation": "Bestemt artikkel i genitiv flertall som spesifiserer 'arbeidene' eller 'møyene'."
      },
      {
        "word": "κόπων",
        "wordId": 26,
        "original": "κόπων",
        "explanation": "Betyr 'strev', 'møye' eller 'hardt arbeid'. Beskriver livets slitsomme byrder og utmattelse."
      },
      {
        "word": "αὐτῶν",
        "wordId": 27,
        "original": "αὐτῶν",
        "explanation": "Personlig pronomen - 'deres'. Refererer til de troende som har kjempet troens kamp."
      },
      {
        "word": "τὰ",
        "wordId": 28,
        "original": "τὰ",
        "explanation": "Bestemt artikkel i nøytrum flertall som innleder 'gjerningene'."
      },
      {
        "word": "γὰρ",
        "wordId": 29,
        "original": "γὰρ",
        "explanation": "Forklarende konjunksjon - 'for'. Gir begrunnelsen for hvorfor de er salige."
      },
      {
        "word": "ἔργα",
        "wordId": 30,
        "original": "ἔργα",
        "explanation": "Betyr 'gjerninger' eller 'handlinger'. De troendes trofaste gjerninger har evig verdi."
      },
      {
        "word": "αὐτῶν",
        "wordId": 31,
        "original": "αὐτῶν",
        "explanation": "Personlig pronomen - 'deres'. Gjerningene tilhører de avdøde troende."
      },
      {
        "word": "ἀκολουθεῖ",
        "wordId": 32,
        "original": "ἀκολουθεῖ",
        "explanation": "Presens av 'akoloutheō' - å følge etter. Gjerningene følger dem inn i evigheten som et varig vitnesbyrd."
      },
      {
        "word": "μετʼ",
        "wordId": 33,
        "original": "μετʼ",
        "explanation": "Preposisjon som betyr 'med' eller 'sammen med'. Gjerningene forblir knyttet til personen."
      },
      {
        "word": "αὐτῶν",
        "wordId": 34,
        "original": "αὐτῶν",
        "explanation": "Personlig pronomen - 'dem'. De troende bærer fruktene av sitt liv med seg for alltid."
      }
    ]
  }
]