[
  {
    "bookId": 19,
    "chapterId": 136,
    "verseId": 22,
    "words": [
      {
        "word": "נַחֲלָה",
        "pronunciation": "na-cha-LAH",
        "wordId": 1,
        "explanation": "Betyr 'arv' eller 'eiendom'. Refererer til det lovede landet som Gud ga Israel som deres evige arv og besittelse."
      },
      {
        "word": "לְיִשְׂרָאֵל",
        "pronunciation": "le-yis-ra-EL",
        "wordId": 2,
        "explanation": "Preposisjonen 'le' (til/for) kombinert med navnet Israel. Navnet betyr 'den som kjemper med Gud' og ble gitt til Jakob etter hans kamp ved Jabbok."
      },
      {
        "word": "עַבְדּוֹ",
        "pronunciation": "av-DO",
        "wordId": 3,
        "explanation": "Sammensatt av 'eved' (tjener) og suffikset 'o' (hans). Israel kalles Guds tjener, en ærestittel som understreker det spesielle paktsforholdet."
      },
      {
        "word": "כִּי",
        "pronunciation": "ki",
        "wordId": 4,
        "explanation": "En konjunksjon som her innleder begrunnelsen - 'for' eller 'fordi'. Gjentas i hver vers som et refreng i denne salmen."
      },
      {
        "word": "לְעוֹלָם",
        "pronunciation": "le-o-LAM",
        "wordId": 5,
        "explanation": "Betyr 'for evig' eller 'til evig tid'. Ordet 'olam' beskriver uendelig tid og brukes for å uttrykke Guds evige natur."
      },
      {
        "word": "חַסְדּוֹ",
        "pronunciation": "chas-DO",
        "wordId": 6,
        "explanation": "Et av Bibelens rikeste ord - 'chesed' (trofast kjærlighet/nåde) med suffikset 'hans'. Beskriver Guds paktsmessige, urokkelige kjærlighet mot sitt folk."
      }
    ]
  }
]