[
  {
    "bookId": 10,
    "chapterId": 22,
    "verseId": 43,
    "words": [
      {
        "word": "Jeg",
        "wordId": 1,
        "original": "וְאֶשְׁחָקֵם",
        "explanation": "Subjektet i setningen, som refererer til David som taler om sin seier over fiendene."
      },
      {
        "word": "malte",
        "wordId": 2,
        "original": "וְאֶשְׁחָקֵם",
        "explanation": "Fra det hebraiske verbet 'shachaq' som betyr å knuse, male eller pulverisere til fine partikler."
      },
      {
        "word": "dem",
        "wordId": 3,
        "original": "וְאֶשְׁחָקֵם",
        "explanation": "Suffikset '-em' indikerer objektet, altså fiendene som blir fullstendig tilintetgjort."
      },
      {
        "word": "til",
        "wordId": 4,
        "original": "כַּעֲפַר",
        "explanation": "Preposisjonen 'ke-' som betyr 'som' eller 'lik', introduserer sammenligningen."
      },
      {
        "word": "støv",
        "wordId": 5,
        "original": "עֲפַר",
        "explanation": "'Afar' beskriver fint jordstøv eller sand, et kraftfullt bilde på total ødeleggelse og menneskets forgjengelighet."
      },
      {
        "word": "for",
        "wordId": 6,
        "original": "אָרֶץ",
        "explanation": "Bindeled i oversettelsen som kobler støvet til vindens bevegelse."
      },
      {
        "word": "vinden",
        "wordId": 7,
        "original": "אָרֶץ",
        "explanation": "Grunnordet 'erets' betyr egentlig 'jord' eller 'land' - oversettelsen tolker uttrykket poetisk."
      },
      {
        "word": "jeg",
        "wordId": 8,
        "original": "אֲדִקֵּם",
        "explanation": "Gjentakelsen av subjektet understreker Davids personlige handling mot fiendene."
      },
      {
        "word": "tømte",
        "wordId": 9,
        "original": "אֲדִקֵּם",
        "explanation": "Verbet 'daqaq' betyr å knuse til småbiter eller stampe ned, et intenst uttrykk for fullstendig seier."
      },
      {
        "word": "dem",
        "wordId": 10,
        "original": "אֲדִקֵּם",
        "explanation": "Objektsuffikset som igjen refererer til de beseirede fiendene."
      },
      {
        "word": "ut",
        "wordId": 11,
        "original": "אֶרְקָעֵם",
        "explanation": "Fra 'raqa' som betyr å stampe ut eller spre tynt, som å hamre ut metall."
      },
      {
        "word": "som",
        "wordId": 12,
        "original": "כְּטִיט",
        "explanation": "Sammenligningspartikkelen 'ke-' innleder det andre bildet av ødeleggelse."
      },
      {
        "word": "skitt",
        "wordId": 13,
        "original": "טִיט",
        "explanation": "'Tit' refererer til leire eller gjørme, noe verdiløst som folk tråkker på i gatene."
      },
      {
        "word": "i",
        "wordId": 14,
        "original": "חוּצוֹת",
        "explanation": "Preposisjon som angir stedet hvor skitten befinner seg."
      },
      {
        "word": "gatene",
        "wordId": 15,
        "original": "חוּצוֹת",
        "explanation": "'Chutsot' betyr åpne plasser eller gater, steder der folk ferdedes og tråkket ned skitten."
      }
    ]
  }
]