[
  {
    "bookId": 41,
    "chapterId": 14,
    "verseId": 7,
    "words": [
      {
        "word": "πάντοτε",
        "wordId": 1,
        "original": "πάντοτε",
        "explanation": "Betyr 'alltid' eller 'til enhver tid', sammensatt av πᾶς (all) og τότε (da), og understreker en kontinuerlig tilstand."
      },
      {
        "word": "γὰρ",
        "wordId": 2,
        "original": "γὰρ",
        "explanation": "En forklarende konjunksjon som betyr 'for' og introduserer begrunnelsen for Jesu forsvar av kvinnens handling."
      },
      {
        "word": "τοὺς",
        "wordId": 3,
        "original": "τοὺς",
        "explanation": "Bestemt artikkel i akkusativ flertall maskulin, peker på en spesifikk gruppe mennesker."
      },
      {
        "word": "πτωχοὺς",
        "wordId": 4,
        "original": "πτωχοὺς",
        "explanation": "Refererer til de fattige eller tiggere, fra verbet πτώσσω (å krype sammen), og beskriver en som er helt avhengig av andres barmhjertighet."
      },
      {
        "word": "ἔχετε",
        "wordId": 5,
        "original": "ἔχετε",
        "explanation": "Et verb som betyr 'dere har' i presens, og indikerer en vedvarende tilstand av å ha de fattige blant seg."
      },
      {
        "word": "μεθʼ",
        "wordId": 6,
        "original": "μεθʼ",
        "explanation": "Forkortet form av μετά før en vokal med pustemark, betyr 'med' eller 'blant'."
      },
      {
        "word": "ἑαυτῶν",
        "wordId": 7,
        "original": "ἑαυτῶν",
        "explanation": "Refleksivt pronomen som betyr 'dere selv', og understreker disiplenes nære forhold til de fattige i samfunnet."
      },
      {
        "word": "καὶ",
        "wordId": 8,
        "original": "καὶ",
        "explanation": "Konjunksjon som knytter sammen setningsledd, her med betydningen 'og'."
      },
      {
        "word": "ὅταν",
        "wordId": 9,
        "original": "ὅταν",
        "explanation": "Betyr 'når som helst' eller 'når', og introduserer en betingelse med fokus på valgfrihet."
      },
      {
        "word": "θέλητε",
        "wordId": 10,
        "original": "θέλητε",
        "explanation": "Konjunktiv form av θέλω som betyr 'dere vil' eller 'dere ønsker', understreker at muligheten alltid vil være der."
      },
      {
        "word": "δύνασθε",
        "wordId": 11,
        "original": "δύνασθε",
        "explanation": "Betyr 'dere kan' eller 'dere er i stand til', fra δύναμαι som er roten til ordet 'dynamikk'."
      },
      {
        "word": "αὐτοῖς",
        "wordId": 12,
        "original": "αὐτοῖς",
        "explanation": "Personlig pronomen i dativ flertall, 'dem', som viser til de fattige som mottakere av velgjerningen."
      },
      {
        "word": "εὖ",
        "wordId": 13,
        "original": "εὖ",
        "explanation": "Adverb som betyr 'godt' eller 'vel', roten til norske ord som 'eufori' og 'eufemisme'."
      },
      {
        "word": "ποιῆσαι",
        "wordId": 14,
        "original": "ποιῆσαι",
        "explanation": "Infinitiv aorist av ποιέω som betyr 'å gjøre', sammen med εὖ danner det uttrykket 'å gjøre godt mot'."
      },
      {
        "word": "ἐμὲ",
        "wordId": 15,
        "original": "ἐμὲ",
        "explanation": "Emfatisk form av 'meg', brukes her for å skape en sterk kontrast mellom Jesus og de fattige."
      },
      {
        "word": "δὲ",
        "wordId": 16,
        "original": "δὲ",
        "explanation": "Kontrasterende konjunksjon som betyr 'men' eller 'derimot', markerer overgangen til den avgjørende kontrasten."
      },
      {
        "word": "οὐ",
        "wordId": 17,
        "original": "οὐ",
        "explanation": "Nektelsespartikkel som betyr 'ikke', brukt i direkte påstander om fakta."
      },
      {
        "word": "πάντοτε",
        "wordId": 18,
        "original": "πάντοτε",
        "explanation": "Gjentagelsen av 'alltid' skaper en poetisk kontrast og understreker at Jesu fysiske nærvær er tidsbegrenset."
      },
      {
        "word": "ἔχετε",
        "wordId": 19,
        "original": "ἔχετε",
        "explanation": "Jesus bruker samme verb som tidligere, men nå negativt, for å peke på sin forestående død og avskjed."
      }
    ]
  }
]