[
  {
    "bookId": 19,
    "chapterId": 85,
    "verseId": 5,
    "words": [
      {
        "word": "שׁוּבֵנוּ",
        "pronunciation": "shu-VE-nu",
        "wordId": 1,
        "explanation": "Et imperativ av verbet 'shuv' (å vende tilbake) med suffiks 'enu' (oss). Betyr 'før oss tilbake' eller 'gjenopprett oss' - en bønn om åndelig fornyelse og gjenopprettelse av forholdet til Gud."
      },
      {
        "word": "אֱלֹהֵי",
        "pronunciation": "elo-HEI",
        "wordId": 2,
        "explanation": "Konstruktformen av 'Elohim' (Gud), som betyr 'Gud til' eller 'vår Gud'. Formen binder sammen gudsnavnet med det følgende ordet og uttrykker et personlig eierforhold."
      },
      {
        "word": "יִשְׁעֵנוּ",
        "pronunciation": "yish-E-nu",
        "wordId": 3,
        "explanation": "Sammensatt av 'yesha' (frelse) og suffikset 'enu' (vår). Refererer til 'vår frelse' - Gud beskrives her som kilden til folkets redning og befrielse."
      },
      {
        "word": "וְהָפֵר",
        "pronunciation": "ve-ha-FER",
        "wordId": 4,
        "explanation": "Konjunksjonen 've' (og) pluss imperativ av 'parar' (å bryte, oppheve, gjøre til intet). Brukes her som en bønn om at Gud skal avbryte eller avslutte sin vrede."
      },
      {
        "word": "כַּעַסְךָ",
        "pronunciation": "ka-as-KHA",
        "wordId": 5,
        "explanation": "Substantivet 'ka'as' (vrede, irritasjon) med suffiks 'kha' (din). Betyr 'din vrede' - et sterkt ord som beskriver Guds harme over folkets synd."
      },
      {
        "word": "עִמָּנוּ",
        "pronunciation": "im-MA-nu",
        "wordId": 6,
        "explanation": "Preposisjonen 'im' (med) kombinert med suffikset 'anu' (oss). Betyr 'med oss' eller 'mot oss' - uttrykker at Guds vrede er rettet mot folket."
      }
    ]
  }
]