[
  {
    "bookId": 24,
    "chapterId": 50,
    "verseId": 18,
    "words": [
      {
        "word": "לָכֵן",
        "pronunciation": "la-KHEN",
        "wordId": 1,
        "explanation": "Betyr 'derfor' eller 'av den grunn'. Brukes for å innlede en konklusjon eller konsekvens av det som er sagt tidligere."
      },
      {
        "word": "כֹּֽה",
        "pronunciation": "koh",
        "wordId": 2,
        "explanation": "Et demonstrativt adverb som betyr 'slik' eller 'dette'. Innleder ofte profetiske utsagn."
      },
      {
        "word": "אָמַר",
        "pronunciation": "a-MAR",
        "wordId": 3,
        "explanation": "Qal perfektum av verbet 'å si'. Den typiske innledningsformelen for profetisk tale i Det gamle testamente."
      },
      {
        "word": "יְהוָה",
        "pronunciation": "Adonai/JHVH",
        "wordId": 4,
        "explanation": "Guds hellige navn, tetragrammet. Uttales tradisjonelt 'Adonai' av ærefrykt. Navnet er avledet fra verbet 'å være' og uttrykker Guds evige eksistens."
      },
      {
        "word": "צְבָאוֹת",
        "pronunciation": "tse-va-OT",
        "wordId": 5,
        "explanation": "Flertall av 'hær' eller 'armé'. I kombinasjon med JHVH betyr det 'hærskarenes Herre', som understreker Guds makt over himmelske og jordiske styrker."
      },
      {
        "word": "אֱלֹהֵי",
        "pronunciation": "e-lo-HEI",
        "wordId": 6,
        "explanation": "Konstruktform av 'Elohim' (Gud), som betyr 'Gud til' eller '...s Gud'. Viser tilhørighet til det følgende ordet."
      },
      {
        "word": "יִשְׂרָאֵל",
        "pronunciation": "yis-ra-EL",
        "wordId": 7,
        "explanation": "Navnet Israel, som betyr 'han kjemper med Gud' eller 'Gud kjemper'. Gitt til Jakob etter hans kamp med engelen."
      },
      {
        "word": "הִנְנִי",
        "pronunciation": "hin-ne-NI",
        "wordId": 8,
        "explanation": "Sammensatt av 'hinneh' (se!) og suffiks for første person. Betyr 'se, jeg' eller 'jeg er i ferd med å'. Uttrykker Guds umiddelbare handling."
      },
      {
        "word": "פֹקֵד",
        "pronunciation": "po-KED",
        "wordId": 9,
        "explanation": "Qal partisipp av 'paqad', et mangesidig verb som kan bety 'å straffe', 'å besøke' eller 'å holde regnskap med'. Her i betydningen dom og straff."
      },
      {
        "word": "אֶל",
        "pronunciation": "el",
        "wordId": 10,
        "explanation": "Preposisjon som betyr 'til', 'mot' eller 'over'. Angir retningen for Guds domshandling."
      },
      {
        "word": "מֶלֶךְ",
        "pronunciation": "ME-lekh",
        "wordId": 11,
        "explanation": "Betyr 'konge'. Et sentralt begrep i bibelske tekster om politisk og åndelig lederskap."
      },
      {
        "word": "בָּבֶל",
        "pronunciation": "ba-VEL",
        "wordId": 12,
        "explanation": "Babylon, hovedstaden i det babylonske riket. Navnet betyr 'Guds port' på akkadisk, men i hebraisk tradisjon forbindes det med forvirring (babel)."
      },
      {
        "word": "וְאֶל",
        "pronunciation": "ve-EL",
        "wordId": 13,
        "explanation": "Konjunksjonen 'og' (ve) kombinert med preposisjonen 'til/mot' (el). Knytter sammen de to objektene for Guds dom."
      },
      {
        "word": "אַרְצוֹ",
        "pronunciation": "ar-TSO",
        "wordId": 14,
        "explanation": "Ordet 'erets' (land) med possessivt suffiks 'hans'. Refererer til kongens land, altså Babylons territorium."
      },
      {
        "word": "כַּאֲשֶׁר",
        "pronunciation": "ka-a-SHER",
        "wordId": 15,
        "explanation": "En sammensatt konjunksjon som betyr 'slik som' eller 'på samme måte som'. Innleder en sammenligning."
      },
      {
        "word": "פָּקַדְתִּי",
        "pronunciation": "pa-KAD-ti",
        "wordId": 16,
        "explanation": "Qal perfektum første person entall av 'paqad'. 'Jeg straffet' eller 'jeg holdt regnskap med'. Viser til Guds tidligere domshandling."
      },
      {
        "word": "אֶל",
        "pronunciation": "el",
        "wordId": 17,
        "explanation": "Preposisjon 'til/mot', som angir objektet for den tidligere domshandlingen."
      },
      {
        "word": "מֶלֶךְ",
        "pronunciation": "ME-lekh",
        "wordId": 18,
        "explanation": "Konge - her refererer det til den assyriske kongen som Gud tidligere hadde straffet."
      },
      {
        "word": "אַשּׁוּר",
        "pronunciation": "ash-SHUR",
        "wordId": 19,
        "explanation": "Assyria, det mektige riket som falt i 612 f.Kr. Navnet kommer fra guden Ashur. Assyrias fall tjener som historisk parallell for Babylons kommende dom."
      }
    ]
  }
]