[
  {
    "bookId": 13,
    "chapterId": 5,
    "verseId": 20,
    "words": [
      {
        "word": "וַיֵּעָזְר֣וּ",
        "wordId": 1,
        "original": "וַיֵּעָזְר֣וּ",
        "explanation": "Et verb i nifal-formen som betyr 'de ble hjulpet' - indikerer at Gud grep inn og ga dem hjelp i krigen."
      },
      {
        "word": "עֲלֵיהֶ֔ם",
        "wordId": 2,
        "original": "עֲלֵיהֶ֔ם",
        "explanation": "Preposisjon med suffiks som betyr 'mot dem' eller 'over dem', refererer til fiendene de kjempet mot."
      },
      {
        "word": "וַיִּנָּתְנ֤וּ",
        "wordId": 3,
        "original": "וַיִּנָּתְנ֤וּ",
        "explanation": "Passiv form av verbet 'natan' (å gi) - betyr 'de ble gitt' eller 'de ble overgitt'."
      },
      {
        "word": "בְיָדָם֙",
        "wordId": 4,
        "original": "בְיָדָם֙",
        "explanation": "Uttrykket 'i deres hånd' er et hebraisk idiom for å ha makt eller kontroll over noen."
      },
      {
        "word": "הַֽהַגְרִיאִ֔ים",
        "wordId": 5,
        "original": "הַֽהַגְרִיאִ֔ים",
        "explanation": "Hagrittene var en arabisk nomadestamme som bodde øst for Jordan, muligens etterkommere av Hagar."
      },
      {
        "word": "וְכֹ֖ל",
        "wordId": 6,
        "original": "וְכֹ֖ל",
        "explanation": "Betyr 'og alle' - inkluderer alle allierte og folk som var sammen med hagrittene."
      },
      {
        "word": "שֶׁ֣עִמָּהֶ֑ם",
        "wordId": 7,
        "original": "שֶׁ֣עִמָּהֶ֑ם",
        "explanation": "Relativpronomen med preposisjon som betyr 'som var med dem'."
      },
      {
        "word": "כִּ֠י",
        "wordId": 8,
        "original": "כִּ֠י",
        "explanation": "Konjunksjon som introduserer årsaken - 'fordi' eller 'for'."
      },
      {
        "word": "לֵאלֹהִ֤ים",
        "wordId": 9,
        "original": "לֵאלֹהִ֤ים",
        "explanation": "Refererer til Gud med preposisjonen 'le' som indikerer retning - 'til Gud'."
      },
      {
        "word": "זָעֲקוּ֙",
        "wordId": 10,
        "original": "זָעֲקוּ֙",
        "explanation": "Et intenst rop om hjelp - sterkere enn vanlig bønn, uttrykker desperat nød i krigens hete."
      },
      {
        "word": "בַּמִּלְחָמָ֔ה",
        "wordId": 11,
        "original": "בַּמִּלְחָמָ֔ה",
        "explanation": "Betyr 'i krigen' - ordet 'milchama' kommer fra roten som betyr 'å kjempe'."
      },
      {
        "word": "וְנַעְתּ֥וֹר",
        "wordId": 12,
        "original": "וְנַעְתּ֥וֹר",
        "explanation": "Sjeldent verb som betyr 'han ble bønnhørt' eller 'han lot seg be' - viser Guds respons på deres rop."
      },
      {
        "word": "לָהֶ֖ם",
        "wordId": 13,
        "original": "לָהֶ֖ם",
        "explanation": "Preposisjon med suffiks som betyr 'for dem' - Gud svarte til deres fordel."
      },
      {
        "word": "כִּי־בָ֥טְחוּ",
        "wordId": 14,
        "original": "כִּי־בָ֥טְחוּ",
        "explanation": "Betyr 'fordi de stolte på' - verbet 'batach' uttrykker dyp tillit og trygghet."
      },
      {
        "word": "בֽוֹ",
        "wordId": 15,
        "original": "בֽוֹ",
        "explanation": "Preposisjon med suffiks som betyr 'på ham' - refererer til deres tillit til Gud."
      }
    ]
  }
]