{
  "bookId": 41,
  "chapterId": 6,
  "verseId": 43,
  "references": [
    {
      "bookId": 40,
      "chapterId": 14,
      "fromVerseId": 20,
      "toVerseId": 20,
      "text": "Beskriver også innsamling av rester etter et mirakuløst måltid, men her fra en annen hendelse."
    },
    {
      "bookId": 41,
      "chapterId": 8,
      "fromVerseId": 8,
      "toVerseId": 9,
      "text": "Ligner på innsamlingen av rester etter et mirakuløst måltid, men fra en annen hendelse med Jesus."
    },
    {
      "bookId": 42,
      "chapterId": 9,
      "fromVerseId": 17,
      "toVerseId": 17,
      "text": "Omtaler innsamling av rester etter et mirakuløst måltid, parallelt til hendelsen i Mark."
    }
  ]
}