[
  {
    "bookId": 10,
    "chapterId": 9,
    "verseId": 10,
    "words": [
      {
        "word": "וְעָבַ֣דְתָּ",
        "wordId": 1,
        "original": "וְעָבַדְתָּ",
        "explanation": "Et verb som betyr 'og du skal dyrke' eller 'og du skal arbeide'. Roten עבד brukes både om arbeid og tjeneste."
      },
      {
        "word": "לּ֣וֹ",
        "wordId": 2,
        "original": "לוֹ",
        "explanation": "Preposisjon med suffiks som betyr 'for ham', og refererer her til Mefiboset."
      },
      {
        "word": "אֶֽת־הָאֲדָמָ֡ה",
        "wordId": 3,
        "original": "אֶת־הָאֲדָמָה",
        "explanation": "Betyr 'jorden' eller 'landet'. Ordet אֲדָמָה er beslektet med אָדָם (menneske) og דָּם (blod)."
      },
      {
        "word": "אַתָּה֩",
        "wordId": 4,
        "original": "אַתָּה",
        "explanation": "Personlig pronomen 'du' i maskulin form, brukt her for å understreke Sibas personlige ansvar."
      },
      {
        "word": "וּבָנֶ֨יךָ",
        "wordId": 5,
        "original": "וּבָנֶיךָ",
        "explanation": "Betyr 'og dine sønner'. Flertallsformen av בֵּן med possessivt suffiks."
      },
      {
        "word": "וַעֲבָדֶ֜יךָ",
        "wordId": 6,
        "original": "וַעֲבָדֶיךָ",
        "explanation": "Refererer til 'og dine tjenere'. Samme rot som verbet i begynnelsen av verset."
      },
      {
        "word": "וְהֵבֵ֗אתָ",
        "wordId": 7,
        "original": "וְהֵבֵאתָ",
        "explanation": "Hifil-formen av בוא, som betyr 'og du skal bringe inn' - en kausativ form som indikerer å få noe til å komme."
      },
      {
        "word": "וְהָיָ֨ה",
        "wordId": 8,
        "original": "וְהָיָה",
        "explanation": "Betyr 'og det skal være' eller 'og det skal bli'. Grunnleggende eksistensverb i hebraisk."
      },
      {
        "word": "לְבֶן־אֲדֹנֶ֤יךָ",
        "wordId": 9,
        "original": "לְבֶן־אֲדֹנֶיךָ",
        "explanation": "Betyr 'for din herres sønn'. אָדוֹן brukes om en herre eller mester, her om Saul."
      },
      {
        "word": "לֶּ֙חֶם֙",
        "wordId": 10,
        "original": "לֶחֶם",
        "explanation": "Ordet for 'brød' brukes ofte som en generell betegnelse for mat og føde i bibelsk hebraisk."
      },
      {
        "word": "וַאֲכָל֔וֹ",
        "wordId": 11,
        "original": "וַאֲכָלוֹ",
        "explanation": "Betyr 'og de skal spise det'. Verbet אכל med suffiks som refererer til maten."
      },
      {
        "word": "וּמְפִיבֹ֙שֶׁת֙",
        "wordId": 12,
        "original": "וּמְפִיבֹשֶׁת",
        "explanation": "Navnet betyr trolig 'den som sprer skam'. Han var Jonatans sønn og Sauls barnebarn, lam i begge føtter."
      },
      {
        "word": "בֶּן־אֲדֹנֶ֔יךָ",
        "wordId": 13,
        "original": "בֶּן־אֲדֹנֶיךָ",
        "explanation": "Gjentakelse av 'din herres sønn', som understreker Mefibosets status som kongelig etterkommer."
      },
      {
        "word": "יֹאכַ֥ל",
        "wordId": 14,
        "original": "יֹאכַל",
        "explanation": "Imperfektum av אכל som betyr 'han skal spise'. Indikerer en vedvarende, fremtidig handling."
      },
      {
        "word": "תָּמִ֛יד",
        "wordId": 15,
        "original": "תָּמִיד",
        "explanation": "Betyr 'alltid' eller 'kontinuerlig'. Brukes ofte i forbindelse med tempeltjenesten for å beskrive det stadige."
      },
      {
        "word": "לֶ֖חֶם",
        "wordId": 16,
        "original": "לֶחֶם",
        "explanation": "Brød som symbol på fullstendig forsørgelse og fellesskap ved kongens bord."
      },
      {
        "word": "עַל־שֻׁלְחָנִ֑י",
        "wordId": 17,
        "original": "עַל־שֻׁלְחָנִי",
        "explanation": "Betyr 'ved mitt bord'. Å spise ved kongens bord var et tegn på stor ære og nær relasjon."
      },
      {
        "word": "וּלְצִיבָ֗א",
        "wordId": 18,
        "original": "וּלְצִיבָא",
        "explanation": "Navnet Siba betyr muligens 'plante' eller 'gren'. Han var tidligere tjener i Sauls hus."
      },
      {
        "word": "חֲמִשָּׁ֥ה",
        "wordId": 19,
        "original": "חֲמִשָּׁה",
        "explanation": "Tallordet 'fem' i maskulin form, brukt her sammen med עָשָׂר for å danne femten."
      },
      {
        "word": "עָשָׂ֛ר",
        "wordId": 20,
        "original": "עָשָׂר",
        "explanation": "Betyr 'ti' når det kombineres med et annet tall for å danne tall mellom 11 og 19."
      },
      {
        "word": "בָּנִ֖ים",
        "wordId": 21,
        "original": "בָּנִים",
        "explanation": "Flertall av בֵּן, 'sønner'. Femten sønner indikerer en stor og velstående husstand."
      },
      {
        "word": "וְעֶשְׂרִ֥ים",
        "wordId": 22,
        "original": "וְעֶשְׂרִים",
        "explanation": "Tallordet 'tjue'. Sammen med femten sønner utgjør dette en betydelig arbeidsstyrke."
      },
      {
        "word": "עֲבָדִֽים",
        "wordId": 23,
        "original": "עֲבָדִים",
        "explanation": "Flertall av עֶבֶד, 'tjenere' eller 'slaver'. Tjue tjenere viser Sibas betydelige ressurser."
      }
    ]
  }
]