[
  {
    "bookId": 13,
    "chapterId": 4,
    "verseId": 18,
    "words": [
      {
        "word": "וְאִשְׁתּ֣וֹ",
        "wordId": 1,
        "original": "וְאִשְׁתּוֹ",
        "explanation": "Betyr 'og hans kone', sammensatt av konjunksjonen 've' (og) og 'ishto' (hans kone)."
      },
      {
        "word": "הַיְהֻדִיָּ֗ה",
        "wordId": 2,
        "original": "הַיְהֻדִיָּה",
        "explanation": "Refererer til 'den jødiske kvinnen' eller 'kvinnen fra Juda', med bestemt artikkel 'ha'."
      },
      {
        "word": "יָלְדָ֞ה",
        "wordId": 3,
        "original": "יָלְדָה",
        "explanation": "Et verb som betyr 'fødte', i perfektum feminin form, fra roten י-ל-ד."
      },
      {
        "word": "אֶת־יֶ֨רֶד",
        "wordId": 4,
        "original": "אֶת־יֶרֶד",
        "explanation": "Navnet Jered betyr 'nedstigning' eller 'den som går ned', muligens relatert til bosetting i lavlandet."
      },
      {
        "word": "אֲבִ֤י",
        "wordId": 5,
        "original": "אֲבִי",
        "explanation": "Betyr 'far til', men brukes ofte i slektstavler for å angi grunnleggeren av en by eller klan."
      },
      {
        "word": "גְדוֹר֙",
        "wordId": 6,
        "original": "גְדוֹר",
        "explanation": "En by i Juda, navnet betyr 'mur' eller 'innhegning', fra roten ג-ד-ר."
      },
      {
        "word": "וְאֶת־חֶ֙בֶר֙",
        "wordId": 7,
        "original": "וְאֶת־חֶבֶר",
        "explanation": "Navnet Heber betyr 'forbindelse' eller 'fellesskap', fra roten ח-ב-ר som handler om å forene."
      },
      {
        "word": "אֲבִ֣י",
        "wordId": 8,
        "original": "אֲבִי",
        "explanation": "Grunnlegger eller stamfar til den følgende byen eller slekten."
      },
      {
        "word": "שׂוֹכ֔וֹ",
        "wordId": 9,
        "original": "שׂוֹכוֹ",
        "explanation": "Soko var en by i Juda-lavlandet, navnet kan bety 'gjerde av torner' eller 'grener'."
      },
      {
        "word": "וְאֶת־יְקֽוּתִיאֵ֖ל",
        "wordId": 10,
        "original": "וְאֶת־יְקוּתִיאֵל",
        "explanation": "Et teoforskt navn som betyr 'Gud vil nære' eller 'lydighet mot Gud'."
      },
      {
        "word": "אֲבִ֣י",
        "wordId": 11,
        "original": "אֲבִי",
        "explanation": "Igjen brukt for å vise stamfarskap til en by."
      },
      {
        "word": "זָנ֑וֹחַ",
        "wordId": 12,
        "original": "זָנוֹחַ",
        "explanation": "En by i Juda, navnet betyr 'forkastet' eller 'forlatt', fra roten ז-נ-ח."
      },
      {
        "word": "וְאֵ֗לֶּה",
        "wordId": 13,
        "original": "וְאֵלֶּה",
        "explanation": "Demonstrativt pronomen som betyr 'og disse', introduserer en oppsummering."
      },
      {
        "word": "בְּנֵי֙",
        "wordId": 14,
        "original": "בְּנֵי",
        "explanation": "Flertallsformen av 'sønn', betyr 'sønner av' eller 'etterkommere av'."
      },
      {
        "word": "בִּתְיָ֣ה",
        "wordId": 15,
        "original": "בִּתְיָה",
        "explanation": "Navnet Bitja betyr 'Herrens datter', et hebraisk navn gitt til faraos datter som konverterte."
      },
      {
        "word": "בַת־פַּרְעֹ֔ה",
        "wordId": 16,
        "original": "בַת־פַּרְעֹה",
        "explanation": "Betyr 'faraos datter', en egyptisk prinsesse som ifølge tradisjonen ble en del av Israels folk."
      },
      {
        "word": "אֲשֶׁ֥ר",
        "wordId": 17,
        "original": "אֲשֶׁר",
        "explanation": "Relativpronomen som betyr 'som' eller 'som han'."
      },
      {
        "word": "לָקַ֖ח",
        "wordId": 18,
        "original": "לָקַח",
        "explanation": "Verbet betyr 'tok' og brukes her i betydningen 'tok til ekte' eller 'giftet seg med'."
      },
      {
        "word": "מָֽרֶד",
        "wordId": 19,
        "original": "מָרֶד",
        "explanation": "Navnet Mered betyr 'opprør', kanskje symbolsk for å ha giftet seg med en egyptisk prinsesse."
      }
    ]
  }
]