[
  {
    "bookId": 4,
    "chapterId": 33,
    "verseId": 4,
    "words": [
      {
        "word": "וּמִצְרַ֣יִם",
        "wordId": 1,
        "original": "וּמִצְרַיִם",
        "explanation": "Betyr 'og Egypt' - navnet kommer muligens fra det hebraiske ordet for 'grenser' eller 'begrensninger', og refererer til landet langs Nilen."
      },
      {
        "word": "מְקַבְּרִ֗ים",
        "wordId": 2,
        "original": "מְקַבְּרִים",
        "explanation": "Et verb i piel partisipp som betyr 'begravde' eller 'holdt på å begrave'. Beskriver den pågående handlingen mens israelittene dro ut."
      },
      {
        "word": "אֵת֩",
        "wordId": 3,
        "original": "אֵת",
        "explanation": "Partikkel som markerer det direkte objektet i setningen, uten egen oversettelse til norsk."
      },
      {
        "word": "אֲשֶׁ֨ר",
        "wordId": 4,
        "original": "אֲשֶׁר",
        "explanation": "Relativpronomen som betyr 'som' eller 'dem som', og kobler sammen hovedsetningen med bisetningen."
      },
      {
        "word": "הִכָּ֧ה",
        "wordId": 5,
        "original": "הִכָּה",
        "explanation": "Verbet betyr 'slo' eller 'slo i hjel' i hifil-formen, og beskriver Guds dødbringende handling mot de førstefødte."
      },
      {
        "word": "יְהוָ֛ה",
        "wordId": 6,
        "original": "יְהוָה",
        "explanation": "Guds hellige navn, ofte uttalt 'Adonai'. Navnet kommer fra verbet 'å være' og uttrykker Guds evige eksistens."
      },
      {
        "word": "בָּהֶ֖ם",
        "wordId": 7,
        "original": "בָּהֶם",
        "explanation": "Preposisjon med pronomen som betyr 'blant dem' eller 'iblant dem', og refererer til egypterne."
      },
      {
        "word": "כָּל־בְּכ֑וֹר",
        "wordId": 8,
        "original": "כָּל־בְּכוֹר",
        "explanation": "Betyr 'hver førstefødt'. Bekhor har spesiell betydning i hebraisk kultur da den førstefødte hadde særlige rettigheter og status."
      },
      {
        "word": "וּבֵאלֹ֣הֵיהֶ֔ם",
        "wordId": 9,
        "original": "וּבֵאלֹהֵיהֶם",
        "explanation": "Refererer til 'og over deres guder' - de egyptiske avgudene. Plagene var også en dom over Egypts falske guder."
      },
      {
        "word": "עָשָׂ֥ה",
        "wordId": 10,
        "original": "עָשָׂה",
        "explanation": "Et vanlig hebraisk verb som betyr 'utførte' eller 'gjorde', her brukt om Guds handlinger."
      },
      {
        "word": "יְהוָ֖ה",
        "wordId": 11,
        "original": "יְהוָה",
        "explanation": "Herrens navn gjentas for å understreke at det var Han som utførte dommen over både mennesker og guder."
      },
      {
        "word": "שְׁפָטִֽים",
        "wordId": 12,
        "original": "שְׁפָטִים",
        "explanation": "Flertallsformen av 'dom' eller 'straff'. Ordet brukes om Guds rettferdige dommer og straff over Egypt."
      }
    ]
  }
]