[
  {
    "bookId": 19,
    "chapterId": 52,
    "verseId": 2,
    "words": [
      {
        "word": "בְּב֤וֹא",
        "pronunciation": "be-vo",
        "wordId": 1,
        "explanation": "Preposisjonen 'ב' (i/da) kombinert med infinitiven 'בוא' (å komme). Uttrykker et tidspunkt: 'da ... kom'."
      },
      {
        "word": "דּוֹאֵ֣ג",
        "pronunciation": "do-eg",
        "wordId": 2,
        "explanation": "Navnet Doeg, som betyr 'engstelig' eller 'bekymret'. Han var en edomitt som tjente kong Saul og ble beryktet for å ha drept prestene i Nob."
      },
      {
        "word": "הָאֲדֹמִי֮",
        "pronunciation": "ha-adomi",
        "wordId": 3,
        "explanation": "Betyr 'edomitten' - en person fra Edom, etterkommere av Esau. Artikkelen 'ה' markerer bestemt form."
      },
      {
        "word": "וַיַּגֵּ֢ד",
        "pronunciation": "va-yag-ged",
        "wordId": 4,
        "explanation": "Et verb i hifil-stammen fra roten נגד, som betyr 'å fortelle' eller 'å rapportere'. Vav-konsekutiv gir narrativ fortidsform."
      },
      {
        "word": "לְשָׁ֫א֥וּל",
        "pronunciation": "le-sha-ul",
        "wordId": 5,
        "explanation": "Preposisjonen 'ל' (til) etterfulgt av navnet Saul, som betyr 'utbedt' eller 'ønsket'. Israels første konge."
      },
      {
        "word": "וַיֹּ֥אמֶר",
        "pronunciation": "va-yo-mer",
        "wordId": 6,
        "explanation": "Standardformelen for direkte tale i hebraisk narrativ - 'og han sa'. Fra roten אמר med vav-konsekutiv."
      },
      {
        "word": "ל֑וֹ",
        "pronunciation": "lo",
        "wordId": 7,
        "explanation": "Preposisjonen 'ל' med 3. person maskulin suffiks, som betyr 'til ham' - refererer tilbake til Saul."
      },
      {
        "word": "בָּ֥א",
        "pronunciation": "ba",
        "wordId": 8,
        "explanation": "Perfektum av verbet בוא (å komme). Indikerer en fullført handling: 'kom' eller 'har kommet'."
      },
      {
        "word": "דָ֝וִ֗ד",
        "pronunciation": "da-vid",
        "wordId": 9,
        "explanation": "Navnet David, som sannsynligvis betyr 'elsket' eller 'onkel'. Den fremtidige kongen som Saul forfulgte av misunnelse."
      },
      {
        "word": "אֶל־בֵּ֥ית",
        "pronunciation": "el-bet",
        "wordId": 10,
        "explanation": "Preposisjonen 'אל' (til) forbundet med 'בית' (hus). 'Til huset' - konstruktform som krever et følgende navn."
      },
      {
        "word": "אֲחִימֶֽלֶךְ",
        "pronunciation": "a-chi-me-lekh",
        "wordId": 11,
        "explanation": "Navnet Akimelek, sammensatt av 'אח' (bror) og 'מלך' (konge), altså 'min bror er konge'. Presten i Nob som hjalp David."
      }
    ]
  }
]