[
  {
    "bookId": 10,
    "chapterId": 22,
    "verseId": 37,
    "words": [
      {
        "word": "תַּרְחִ֥יב",
        "wordId": 1,
        "original": "תַּרְחִ֥יב",
        "explanation": "Et verb i hifil-form som betyr 'du gjør vid' eller 'du utvider'. Roten ר-ח-ב handler om bredde og romslighet."
      },
      {
        "word": "צַעֲדִ֖י",
        "wordId": 2,
        "original": "צַעֲדִ֖י",
        "explanation": "Betyr 'mitt skritt' eller 'min gang'. Substantivet צַעַד refererer til hvert enkelt steg en person tar."
      },
      {
        "word": "תַּחְתֵּ֑נִי",
        "wordId": 3,
        "original": "תַּחְתֵּ֑נִי",
        "explanation": "Sammensatt av תַּחַת (under) og suffikset 'meg'. Refererer til området under føttene, altså grunnlaget man står på."
      },
      {
        "word": "וְלֹ֥א",
        "wordId": 4,
        "original": "וְלֹ֥א",
        "explanation": "Konjunksjonen 'og' (וְ) kombinert med nektelsen 'ikke' (לֹא). Introduserer en negativ setning."
      },
      {
        "word": "מָעֲד֖וּ",
        "wordId": 5,
        "original": "מָעֲד֖וּ",
        "explanation": "Verb som betyr 'vaklet' eller 'skled'. Roten מ-ע-ד beskriver ustøhet og tap av fotfeste."
      },
      {
        "word": "קַרְסֻלָּֽי",
        "wordId": 6,
        "original": "קַרְסֻלָּֽי",
        "explanation": "Betyr 'mine ankler'. Dette ordet forekommer sjelden i Bibelen og refererer til den nedre delen av beinet som gir stabilitet."
      }
    ]
  }
]