[
  {
    "bookId": 12,
    "chapterId": 17,
    "verseId": 18,
    "words": [
      {
        "word": "וַיִּתְאַנַּף",
        "wordId": 1,
        "original": "וַיִּתְאַנַּף",
        "explanation": "Et verb i hitpael-form som uttrykker intens vrede. Roten אנף beskriver en dyp, vedvarende harme, ofte brukt om Guds vrede mot synd."
      },
      {
        "word": "יְהוָה",
        "wordId": 2,
        "original": "יְהוָה",
        "explanation": "Guds hellige navn, tetragrammet YHWH. Dette navnet åpenbarer Gud som den evige, selveksisterende og paktsholdende Gud."
      },
      {
        "word": "מְאֹד",
        "wordId": 3,
        "original": "מְאֹד",
        "explanation": "Betyr 'veldig' eller 'i høy grad', og forsterker intensiteten av Herrens vrede mot Israels vedvarende ulydighet."
      },
      {
        "word": "בְּיִשְׂרָאֵל",
        "wordId": 4,
        "original": "בְּיִשְׂרָאֵל",
        "explanation": "Refererer til nordriket Israel, som her står under Guds dom. Preposisjonen ב angir objektet for Guds vrede."
      },
      {
        "word": "וַיְסִרֵם",
        "wordId": 5,
        "original": "וַיְסִרֵם",
        "explanation": "Fra roten סור som betyr 'å fjerne' eller 'vende bort'. Suffikset -ם refererer til Israel som ble sendt i eksil."
      },
      {
        "word": "מֵעַל",
        "wordId": 6,
        "original": "מֵעַל",
        "explanation": "En sammensatt preposisjon som betyr 'bort fra' eller 'vekk fra', og markerer separasjon fra Guds nærvær."
      },
      {
        "word": "פָּנָיו",
        "wordId": 7,
        "original": "פָּנָיו",
        "explanation": "Betyr 'hans ansikt' og symboliserer Guds nærvær og velbehag. Å bli fjernet fra Guds ansikt innebærer tap av hans beskyttelse."
      },
      {
        "word": "לֹא",
        "wordId": 8,
        "original": "לֹא",
        "explanation": "Nektelsespartikkelen som brukes for å innlede den påfølgende beskrivelsen av hva som gjenstod."
      },
      {
        "word": "נִשְׁאַר",
        "wordId": 9,
        "original": "נִשְׁאַר",
        "explanation": "Verbet betyr 'ble igjen' eller 'gjensto'. Nifal-formen indikerer passiv handling - det som var tilbake etter dommen."
      },
      {
        "word": "רַק",
        "wordId": 10,
        "original": "רַק",
        "explanation": "Begrensende partikkel som betyr 'bare' eller 'kun', og understreker hvor lite som var igjen av Guds folk."
      },
      {
        "word": "שֵׁבֶט",
        "wordId": 11,
        "original": "שֵׁבֶט",
        "explanation": "Betyr 'stamme' og refererer opprinnelig til en hyrdes stav. Brukes om Israels tolv stammer som separate slektslinjer."
      },
      {
        "word": "יְהוּדָה",
        "wordId": 12,
        "original": "יְהוּדָה",
        "explanation": "Navnet betyr 'pris' eller 'takksigelse'. Juda-stammen ble spart på grunn av Guds løfte til David om et evig dynasti."
      },
      {
        "word": "לְבַדּוֹ",
        "wordId": 13,
        "original": "לְבַדּֽוֹ",
        "explanation": "Betyr 'alene' eller 'for seg selv'. Suffikset refererer til Juda som den eneste gjenværende stammen i landet."
      }
    ]
  }
]