[
  {
    "bookId": 26,
    "chapterId": 48,
    "verseId": 20,
    "words": [
      {
        "word": "כָּל",
        "pronunciation": "kol",
        "wordId": 1,
        "explanation": "Betyr 'hele' eller 'all'. Brukes her for å indikere totaliteten av det avgrensede området som beskrives."
      },
      {
        "word": "הַתְּרוּמָה",
        "pronunciation": "hat-terumah",
        "wordId": 2,
        "explanation": "Med bestemt artikkel 'ha-' betyr dette 'offergaven' eller 'det avsatte området'. Terumah refererer til noe som er løftet opp eller satt til side som hellig gave."
      },
      {
        "word": "חֲמִשָּׁה",
        "pronunciation": "chamishah",
        "wordId": 3,
        "explanation": "Tallet fem i hankjønnsform. Her brukt som del av det sammensatte tallet 'tjuefem'."
      },
      {
        "word": "וְעֶשְׂרִים",
        "pronunciation": "ve-esrim",
        "wordId": 4,
        "explanation": "Konjunksjonen 've-' (og) pluss 'esrim' (tjue). Sammen med forrige ord: tjuefem (tusen)."
      },
      {
        "word": "אֶלֶף",
        "pronunciation": "elef",
        "wordId": 5,
        "explanation": "Betyr 'tusen'. Brukes her som måleenhet for det hellige områdets dimensjoner."
      },
      {
        "word": "בַּחֲמִשָּׁה",
        "pronunciation": "ba-chamishah",
        "wordId": 6,
        "explanation": "Preposisjonen 'be-' (i/med) med bestemt artikkel og tallet fem. Angir den andre dimensjonen av området."
      },
      {
        "word": "וְעֶשְׂרִים",
        "pronunciation": "ve-esrim",
        "wordId": 7,
        "explanation": "Igjen 'og tjue', som gir tjuefem. Området er altså kvadratisk: 25 000 x 25 000."
      },
      {
        "word": "אָלֶף",
        "pronunciation": "alef",
        "wordId": 8,
        "explanation": "Tusen - gjentar måleenheten for den andre dimensjonen av det firkantede området."
      },
      {
        "word": "רְבִיעִית",
        "pronunciation": "revi'it",
        "wordId": 9,
        "explanation": "En fjerdedel eller firedelt. Refererer til den firkantede formen på området som beskrives."
      },
      {
        "word": "תָּרִימוּ",
        "pronunciation": "tarimu",
        "wordId": 10,
        "explanation": "Et verb i hifil-stammen, 2. person flertall: 'dere skal løfte opp/avsette'. Kommer fra samme rot som terumah og indikerer handlingen å sette noe til side som hellig."
      },
      {
        "word": "אֶת",
        "pronunciation": "et",
        "wordId": 11,
        "explanation": "Akkusativmarkør som peker ut det direkte objektet i setningen - her offergaven."
      },
      {
        "word": "תְּרוּמַת",
        "pronunciation": "terumat",
        "wordId": 12,
        "explanation": "Konstruktform av terumah: 'offergaven til' eller 'det avsatte området for'. Knytter seg til det følgende ordet."
      },
      {
        "word": "הַקֹּדֶשׁ",
        "pronunciation": "hak-kodesh",
        "wordId": 13,
        "explanation": "Med bestemt artikkel: 'det hellige' eller 'helligdommen'. Kodesh betegner det som er atskilt og viet til Gud."
      },
      {
        "word": "אֶל",
        "pronunciation": "el",
        "wordId": 14,
        "explanation": "Preposisjon som betyr 'til' eller 'mot'. Angir retning eller tilhørighet."
      },
      {
        "word": "אֲחֻזַּת",
        "pronunciation": "achuzzat",
        "wordId": 15,
        "explanation": "Konstruktform av achuzzah: 'eiendommen til' eller 'besittelsen av'. Refererer til det tildelte landområdet."
      },
      {
        "word": "הָעִיר",
        "pronunciation": "ha-ir",
        "wordId": 16,
        "explanation": "Med bestemt artikkel: 'byen'. Refererer til den fremtidige byen i Esekiels visjon om det gjenopprettede landet."
      }
    ]
  }
]