[
  {
    "bookId": 1,
    "chapterId": 34,
    "verseId": 24,
    "words": [
      {
        "word": "Alle",
        "wordId": 1,
        "original": "כָּל",
        "explanation": "Betyr «alle» eller «enhver», og understreker her at hele byens mannlige befolkning deltok i beslutningen."
      },
      {
        "word": "som",
        "wordId": 2,
        "original": "-",
        "explanation": "Norsk relativpronomen lagt til for å gjøre setningen grammatisk korrekt."
      },
      {
        "word": "gikk",
        "wordId": 3,
        "original": "יֹצְאֵי",
        "explanation": "Partisippformen av verbet «yatsa» som betyr å gå ut. Uttrykket «de som går ut av porten» refererer til de voksne mennene som hadde stemmerett i byens anliggender."
      },
      {
        "word": "ut",
        "wordId": 4,
        "original": "יֹצְאֵי",
        "explanation": "Del av det hebraiske uttrykket for dem som deltar i byens offentlige liv."
      },
      {
        "word": "av",
        "wordId": 5,
        "original": "-",
        "explanation": "Norsk preposisjon som kobler handlingen til stedet."
      },
      {
        "word": "byporten",
        "wordId": 6,
        "original": "שַׁעַר עִירוֹ",
        "explanation": "Byporten var det sentrale møtestedet i antikke byer hvor juridiske og politiske beslutninger ble tatt. Her samlet byens ledende menn seg."
      },
      {
        "word": "hørte",
        "wordId": 7,
        "original": "וַיִּשְׁמְעוּ",
        "explanation": "Verbet «shama» betyr ikke bare å høre, men også å adlyde eller samtykke. Folket aksepterte forslaget fra sine ledere."
      },
      {
        "word": "på",
        "wordId": 8,
        "original": "אֶל",
        "explanation": "Preposisjonen «el» indikerer retning mot noen, her brukt for å vise hvem de lyttet til."
      },
      {
        "word": "Hamor",
        "wordId": 9,
        "original": "חֲמוֹר",
        "explanation": "Navnet betyr «esel» på hebraisk, som i antikken var et symbol på handel og rikdom, passende for en hersker."
      },
      {
        "word": "og",
        "wordId": 10,
        "original": "וְ",
        "explanation": "Konjunksjonen «vav» binder sammen de to personene folket lyttet til."
      },
      {
        "word": "hans",
        "wordId": 11,
        "original": "בְּנוֹ",
        "explanation": "Eiendomspronomenet viser familieforholdet mellom Hamor og Sikem."
      },
      {
        "word": "sønn",
        "wordId": 12,
        "original": "בְּנוֹ",
        "explanation": "«Ben» refererer til Sikem som arving til Hamors posisjon og den som ønsket å gifte seg med Dina."
      },
      {
        "word": "Sikem",
        "wordId": 13,
        "original": "שְׁכֶם",
        "explanation": "Navnet betyr «skulder» eller «rygg» og refererer også til byens beliggenhet mellom to fjell. Han er prinsen som voldtok Dina."
      },
      {
        "word": "og",
        "wordId": 14,
        "original": "וַ",
        "explanation": "Konjunksjonen markerer overgangen til handlingens resultat."
      },
      {
        "word": "hver",
        "wordId": 15,
        "original": "כָּל",
        "explanation": "Gjentar totaliteten av dem som ble omskåret."
      },
      {
        "word": "mannlig",
        "wordId": 16,
        "original": "זָכָר",
        "explanation": "«Zakhar» refererer spesifikt til hankjønn og understreker at omskjærelsen gjaldt alle menn i byen."
      },
      {
        "word": "ble",
        "wordId": 17,
        "original": "וַיִּמֹּלוּ",
        "explanation": "Del av verbformen som uttrykker den passive handlingen av omskjærelse."
      },
      {
        "word": "omskåret",
        "wordId": 18,
        "original": "וַיִּמֹּלוּ",
        "explanation": "Verbet «mul» beskriver omskjærelsesritualet som var paktstegnet for Abraham og hans etterkommere, men her utført på hedninger."
      },
      {
        "word": "alle",
        "wordId": 19,
        "original": "כָּל",
        "explanation": "Repetisjon som forsterker at absolutt alle menn i byen gjennomgikk ritualet."
      },
      {
        "word": "som",
        "wordId": 20,
        "original": "-",
        "explanation": "Norsk relativpronomen i den gjentatte frasen."
      },
      {
        "word": "gikk",
        "wordId": 21,
        "original": "יֹצְאֵי",
        "explanation": "Gjentakelsen av uttrykket «de som går ut av porten» bekrefter at alle beslutningsdyktige menn deltok."
      },
      {
        "word": "ut",
        "wordId": 22,
        "original": "יֹצְאֵי",
        "explanation": "Del av det idiomatiske uttrykket for byens borgere."
      },
      {
        "word": "av",
        "wordId": 23,
        "original": "-",
        "explanation": "Preposisjon som forbinder handlingen med stedet."
      },
      {
        "word": "byporten",
        "wordId": 24,
        "original": "שַׁעַר עִירוֹ",
        "explanation": "Den avsluttende gjentakelsen understreker at hele samfunnet gikk med på avtalen, noe som gjorde dem sårbare for det kommende angrepet."
      }
    ]
  }
]